cgd_creator/__init__.py
cgd_creator/cli.py
cgd_creator-0.0.1.dist-info/METADATA
cgd_creator-0.0.1.dist-info/WHEEL
cgd_creator-0.0.1.dist-info/entry_points.txt
cgd_creator-0.0.1.dist-info/RECORD
