Metadata-Version: 2.4
Name: cgd-creator
Version: 0.0.1
Summary: Create Clarity-Gated Documents (.cgd) with epistemic markers for safe LLM ingestion
Project-URL: Homepage, https://github.com/frmoretto/clarity-gate
Project-URL: Repository, https://github.com/frmoretto/clarity-gate
Project-URL: Documentation, https://github.com/frmoretto/clarity-gate/blob/main/docs/CGD_FORMAT.md
Project-URL: Issues, https://github.com/frmoretto/clarity-gate/issues
Author-email: Francesco Marinoni Moretto <francesco@fmmconsulting.it>
License-Expression: CC-BY-4.0
Keywords: ai-safety,cgd,clarity-gate,creator,documentation,epistemic,llm,rag
Classifier: Development Status :: 1 - Planning
Classifier: Intended Audience :: Developers
Classifier: Programming Language :: Python :: 3
Classifier: Programming Language :: Python :: 3.9
Classifier: Programming Language :: Python :: 3.10
Classifier: Programming Language :: Python :: 3.11
Classifier: Programming Language :: Python :: 3.12
Classifier: Topic :: Documentation
Classifier: Topic :: Scientific/Engineering :: Artificial Intelligence
Requires-Python: >=3.9
